ucla_geotech_tools_random_field-1.0.5-py3.6-nspkg.pth
ucla_geotech_tools/random_field.cpython-36m-darwin.so
ucla_geotech_tools_random_field-1.0.5.dist-info/METADATA
ucla_geotech_tools_random_field-1.0.5.dist-info/WHEEL
ucla_geotech_tools_random_field-1.0.5.dist-info/namespace_packages.txt
ucla_geotech_tools_random_field-1.0.5.dist-info/top_level.txt
ucla_geotech_tools_random_field-1.0.5.dist-info/RECORD
