Metadata-Version: 2.1
Name: ucla-geotech-tools-random-field
Version: 1.0.5
Summary: Randosm field generation
Home-page: UNKNOWN
Author: Yang Yang
Author-email: dienyoung@outlook.com
License: MIT
Platform: UNKNOWN
